amsdal_storages/Third-Party Materials - AMSDAL Dependencies - License Notices.md
amsdal_storages/__about__.py
amsdal_storages/__init__.py
amsdal_storages/py.typed
amsdal_storages/s3/__init__.py
amsdal_storages/s3/storage.py
amsdal_storages-0.1.1.dist-info/METADATA
amsdal_storages-0.1.1.dist-info/WHEEL
amsdal_storages-0.1.1.dist-info/RECORD
