Metadata-Version: 2.4
Name: amsdal_storages
Version: 0.1.1
Summary: amsdal_storages plugin for AMSDAL Framework
Requires-Python: >=3.11
Requires-Dist: amsdal-models>=0.5.16
Requires-Dist: amsdal[cli]>=0.5.10
Provides-Extra: s3
Requires-Dist: aioboto3>=11.0.0; extra == 's3'
Requires-Dist: boto3; extra == 's3'
